{
  "$schema": "https://ui.shadcn.com/schema/registry-item.json",
  "name": "account",
  "description": "Account settings and security components.",
  "dependencies": [
    "better-auth",
    "better-auth-ui",
    "lucide-react",
    "zod",
    "react-hook-form",
    "@hookform/resolvers"
  ],
  "registryDependencies": [
    "button",
    "card",
    "input",
    "label",
    "tabs",
    "separator",
    "dialog",
    "skeleton",
    "table",
    "badge"
  ],
  "files": [
    {
      "path": "registry/source/settings/account-settings-cards.tsx",
      "content": "\"use client\"\r\n\r\nimport { useContext } from \"react\"\r\n\r\nimport { AuthUIContext } from \"better-auth-ui\"\r\nimport { cn } from \"better-auth-ui\"\r\nimport type { AuthLocalization } from \"better-auth-ui\"\r\nimport { AccountsCard } from \"@/components/account/accounts-card\"\r\nimport { UpdateAvatarCard } from \"@/components/account/update-avatar-card\"\r\nimport { UpdateFieldCard } from \"@/components/account/update-field-card\"\r\nimport { UpdateNameCard } from \"@/components/account/update-name-card\"\r\nimport { UpdateUsernameCard } from \"@/components/account/update-username-card\"\r\nimport { ChangeEmailCard } from \"./security/change-email-card\"\r\nimport type { SettingsCardClassNames } from \"./shared/settings-card\"\r\n\r\nexport interface AccountSettingsCardsProps {\r\n    className?: string\r\n    classNames?: {\r\n        card?: SettingsCardClassNames\r\n        cards?: string\r\n    }\r\n    localization?: Partial<AuthLocalization>\r\n}\r\n\r\nexport function AccountSettingsCards({\r\n    className,\r\n    classNames,\r\n    localization\r\n}: AccountSettingsCardsProps) {\r\n    const {\r\n        additionalFields,\r\n        avatar,\r\n        changeEmail,\r\n        credentials,\r\n        hooks: { useSession },\r\n        multiSession,\r\n        account: accountOptions\r\n    } = useContext(AuthUIContext)\r\n\r\n    const { data: sessionData } = useSession()\r\n\r\n    return (\r\n        <div\r\n            className={cn(\r\n                \"flex w-full flex-col gap-4 md:gap-6\",\r\n                className,\r\n                classNames?.cards\r\n            )}\r\n        >\r\n            {accountOptions?.fields?.includes(\"image\") && avatar && (\r\n                <UpdateAvatarCard\r\n                    classNames={classNames?.card}\r\n                    localization={localization}\r\n                />\r\n            )}\r\n\r\n            {credentials?.username && (\r\n                <UpdateUsernameCard\r\n                    classNames={classNames?.card}\r\n                    localization={localization}\r\n                />\r\n            )}\r\n\r\n            {accountOptions?.fields?.includes(\"name\") && (\r\n                <UpdateNameCard\r\n                    classNames={classNames?.card}\r\n                    localization={localization}\r\n                />\r\n            )}\r\n\r\n            {changeEmail && (\r\n                <ChangeEmailCard\r\n                    classNames={classNames?.card}\r\n                    localization={localization}\r\n                />\r\n            )}\r\n\r\n            {accountOptions?.fields?.map((field) => {\r\n                if (field === \"image\") return null\r\n                if (field === \"name\") return null\r\n                const additionalField = additionalFields?.[field]\r\n                if (!additionalField) return null\r\n\r\n                const {\r\n                    label,\r\n                    description,\r\n                    instructions,\r\n                    placeholder,\r\n                    required,\r\n                    type,\r\n                    multiline,\r\n                    validate\r\n                } = additionalField\r\n\r\n                // @ts-expect-error Custom fields are not typed\r\n                const defaultValue = sessionData?.user[field] as unknown\r\n\r\n                return (\r\n                    <UpdateFieldCard\r\n                        key={field}\r\n                        classNames={classNames?.card}\r\n                        value={defaultValue}\r\n                        description={description}\r\n                        name={field}\r\n                        instructions={instructions}\r\n                        label={label}\r\n                        localization={localization}\r\n                        placeholder={placeholder}\r\n                        required={required}\r\n                        type={type}\r\n                        multiline={multiline}\r\n                        validate={validate}\r\n                    />\r\n                )\r\n            })}\r\n\r\n            {multiSession && (\r\n                <AccountsCard\r\n                    classNames={classNames?.card}\r\n                    localization={localization}\r\n                />\r\n            )}\r\n        </div>\r\n    )\r\n}\r\n",
      "type": "registry:component",
      "target": "components/settings/account-settings-cards.tsx"
    },
    {
      "path": "registry/source/settings/security-settings-cards.tsx",
      "content": "\"use client\"\r\n\r\nimport { useContext } from \"react\"\r\nimport { AuthUIContext } from \"better-auth-ui\"\r\nimport { cn } from \"better-auth-ui\"\r\nimport type { AuthLocalization } from \"better-auth-ui\"\r\nimport { DeleteAccountCard } from \"@/components/account/delete-account-card\"\r\nimport { PasskeysCard } from \"./passkey/passkeys-card\"\r\nimport { ProvidersCard } from \"./providers/providers-card\"\r\nimport { ChangePasswordCard } from \"./security/change-password-card\"\r\nimport { SessionsCard } from \"./security/sessions-card\"\r\nimport type { SettingsCardClassNames } from \"./shared/settings-card\"\r\nimport { TwoFactorCard } from \"./two-factor/two-factor-card\"\r\n\r\nexport function SecuritySettingsCards({\r\n    className,\r\n    classNames,\r\n    localization\r\n}: {\r\n    className?: string\r\n    classNames?: {\r\n        card?: SettingsCardClassNames\r\n        cards?: string\r\n    }\r\n    localization?: Partial<AuthLocalization>\r\n}) {\r\n    const {\r\n        credentials,\r\n        deleteUser,\r\n        hooks,\r\n        localization: contextLocalization,\r\n        passkey,\r\n        social,\r\n        genericOAuth,\r\n        twoFactor\r\n    } = useContext(AuthUIContext)\r\n\r\n    localization = { ...contextLocalization, ...localization }\r\n\r\n    const { useListAccounts } = hooks\r\n\r\n    const {\r\n        data: accounts,\r\n        isPending: accountsPending,\r\n        refetch: refetchAccounts\r\n    } = useListAccounts()\r\n\r\n    const credentialsLinked = accounts?.some(\r\n        (acc) => acc.providerId === \"credential\"\r\n    )\r\n\r\n    return (\r\n        <div\r\n            className={cn(\r\n                \"flex w-full flex-col gap-4 md:gap-6\",\r\n                className,\r\n                classNames?.cards\r\n            )}\r\n        >\r\n            {credentials && (\r\n                <ChangePasswordCard\r\n                    accounts={accounts}\r\n                    classNames={classNames?.card}\r\n                    isPending={accountsPending}\r\n                    localization={localization}\r\n                    skipHook\r\n                />\r\n            )}\r\n\r\n            {(social?.providers?.length || genericOAuth?.providers?.length) && (\r\n                <ProvidersCard\r\n                    accounts={accounts}\r\n                    classNames={classNames?.card}\r\n                    isPending={accountsPending}\r\n                    localization={localization}\r\n                    refetch={refetchAccounts}\r\n                    skipHook\r\n                />\r\n            )}\r\n\r\n            {twoFactor && credentialsLinked && (\r\n                <TwoFactorCard\r\n                    classNames={classNames?.card}\r\n                    localization={localization}\r\n                />\r\n            )}\r\n\r\n            {passkey && (\r\n                <PasskeysCard\r\n                    classNames={classNames?.card}\r\n                    localization={localization}\r\n                />\r\n            )}\r\n\r\n            <SessionsCard\r\n                classNames={classNames?.card}\r\n                localization={localization}\r\n            />\r\n\r\n            {deleteUser && (\r\n                <DeleteAccountCard\r\n                    accounts={accounts}\r\n                    classNames={classNames?.card}\r\n                    isPending={accountsPending}\r\n                    localization={localization}\r\n                    skipHook\r\n                />\r\n            )}\r\n        </div>\r\n    )\r\n}\r\n",
      "type": "registry:component",
      "target": "components/settings/security-settings-cards.tsx"
    },
    {
      "path": "registry/source/settings/security/change-email-card.tsx",
      "content": "\"use client\"\r\n\r\nimport { zodResolver } from \"@hookform/resolvers/zod\"\r\nimport { useContext, useState } from \"react\"\r\nimport { useForm } from \"react-hook-form\"\r\nimport * as z from \"zod\"\r\nimport { AuthUIContext } from \"better-auth-ui\"\r\nimport { cn, getLocalizedError } from \"better-auth-ui\"\r\nimport { CardContent } from \"@/components/ui/card\"\r\nimport {\r\n    Form,\r\n    FormControl,\r\n    FormField,\r\n    FormItem,\r\n    FormMessage\r\n} from \"@/components/ui/form\"\r\nimport { Input } from \"@/components/ui/input\"\r\nimport { Skeleton } from \"@/components/ui/skeleton\"\r\nimport type { SettingsCardProps } from \"../shared/settings-card\"\r\nimport { SettingsCard } from \"../shared/settings-card\"\r\n\r\nexport type ChangeEmailCardProps = SettingsCardProps\r\n\r\nexport function ChangeEmailCard({\r\n    className,\r\n    classNames,\r\n    localization,\r\n    ...props\r\n}: SettingsCardProps) {\r\n    const {\r\n        authClient,\r\n        emailVerification,\r\n        hooks: { useSession },\r\n        localization: contextLocalization,\r\n        toast\r\n    } = useContext(AuthUIContext)\r\n\r\n    localization = { ...contextLocalization, ...localization }\r\n\r\n    const { data: sessionData, isPending, refetch } = useSession()\r\n    const [resendDisabled, setResendDisabled] = useState(false)\r\n\r\n    const formSchema = z.object({\r\n        email: z.string().email({ message: localization.INVALID_EMAIL })\r\n    })\r\n\r\n    const form = useForm({\r\n        resolver: zodResolver(formSchema),\r\n        values: {\r\n            email: sessionData?.user.email || \"\"\r\n        }\r\n    })\r\n\r\n    const resendForm = useForm()\r\n\r\n    const { isSubmitting } = form.formState\r\n\r\n    const changeEmail = async ({ email }: z.infer<typeof formSchema>) => {\r\n        if (email === sessionData?.user.email) {\r\n            await new Promise((resolve) => setTimeout(resolve))\r\n            toast({\r\n                variant: \"error\",\r\n                message: localization.EMAIL_IS_THE_SAME\r\n            })\r\n            return\r\n        }\r\n\r\n        try {\r\n            await authClient.changeEmail({\r\n                newEmail: email,\r\n                callbackURL: window.location.pathname,\r\n                fetchOptions: { throw: true }\r\n            })\r\n\r\n            if (sessionData?.user.emailVerified) {\r\n                toast({\r\n                    variant: \"success\",\r\n                    message: localization.EMAIL_VERIFY_CHANGE!\r\n                })\r\n            } else {\r\n                await refetch?.()\r\n                toast({\r\n                    variant: \"success\",\r\n                    message: `${localization.EMAIL} ${localization.UPDATED_SUCCESSFULLY}`\r\n                })\r\n            }\r\n        } catch (error) {\r\n            toast({\r\n                variant: \"error\",\r\n                message: getLocalizedError({ error, localization })\r\n            })\r\n        }\r\n    }\r\n\r\n    const resendVerification = async () => {\r\n        if (!sessionData) return\r\n        const email = sessionData.user.email\r\n\r\n        setResendDisabled(true)\r\n\r\n        try {\r\n            await authClient.sendVerificationEmail({\r\n                email,\r\n                fetchOptions: { throw: true }\r\n            })\r\n\r\n            toast({\r\n                variant: \"success\",\r\n                message: localization.EMAIL_VERIFICATION!\r\n            })\r\n        } catch (error) {\r\n            toast({\r\n                variant: \"error\",\r\n                message: getLocalizedError({ error, localization })\r\n            })\r\n            setResendDisabled(false)\r\n            throw error\r\n        }\r\n    }\r\n\r\n    return (\r\n        <>\r\n            <Form {...form}>\r\n                <form noValidate onSubmit={form.handleSubmit(changeEmail)}>\r\n                    <SettingsCard\r\n                        className={className}\r\n                        classNames={classNames}\r\n                        description={localization.EMAIL_DESCRIPTION}\r\n                        instructions={localization.EMAIL_INSTRUCTIONS}\r\n                        isPending={isPending}\r\n                        title={localization.EMAIL}\r\n                        actionLabel={localization.SAVE}\r\n                        {...props}\r\n                    >\r\n                        <CardContent className={classNames?.content}>\r\n                            {isPending ? (\r\n                                <Skeleton\r\n                                    className={cn(\r\n                                        \"h-9 w-full\",\r\n                                        classNames?.skeleton\r\n                                    )}\r\n                                />\r\n                            ) : (\r\n                                <FormField\r\n                                    control={form.control}\r\n                                    name=\"email\"\r\n                                    render={({ field }) => (\r\n                                        <FormItem>\r\n                                            <FormControl>\r\n                                                <Input\r\n                                                    className={\r\n                                                        classNames?.input\r\n                                                    }\r\n                                                    placeholder={\r\n                                                        localization.EMAIL_PLACEHOLDER\r\n                                                    }\r\n                                                    type=\"email\"\r\n                                                    disabled={isSubmitting}\r\n                                                    {...field}\r\n                                                />\r\n                                            </FormControl>\r\n\r\n                                            <FormMessage\r\n                                                className={classNames?.error}\r\n                                            />\r\n                                        </FormItem>\r\n                                    )}\r\n                                />\r\n                            )}\r\n                        </CardContent>\r\n                    </SettingsCard>\r\n                </form>\r\n            </Form>\r\n\r\n            {emailVerification &&\r\n                sessionData?.user &&\r\n                !sessionData?.user.emailVerified && (\r\n                    <Form {...resendForm}>\r\n                        <form\r\n                            onSubmit={resendForm.handleSubmit(\r\n                                resendVerification\r\n                            )}\r\n                        >\r\n                            <SettingsCard\r\n                                className={className}\r\n                                classNames={classNames}\r\n                                title={localization.VERIFY_YOUR_EMAIL}\r\n                                description={\r\n                                    localization.VERIFY_YOUR_EMAIL_DESCRIPTION\r\n                                }\r\n                                actionLabel={\r\n                                    localization.RESEND_VERIFICATION_EMAIL\r\n                                }\r\n                                disabled={resendDisabled}\r\n                                {...props}\r\n                            />\r\n                        </form>\r\n                    </Form>\r\n                )}\r\n        </>\r\n    )\r\n}\r\n",
      "type": "registry:component",
      "target": "components/settings/security/change-email-card.tsx"
    },
    {
      "path": "registry/source/settings/security/change-password-card.tsx",
      "content": "\"use client\"\r\n\r\nimport { zodResolver } from \"@hookform/resolvers/zod\"\r\nimport { useContext } from \"react\"\r\nimport { useForm } from \"react-hook-form\"\r\nimport * as z from \"zod\"\r\n\r\nimport { AuthUIContext } from \"better-auth-ui\"\r\nimport { cn, getLocalizedError, getPasswordSchema } from \"better-auth-ui\"\r\nimport type { AuthLocalization } from \"better-auth-ui\"\r\nimport type { PasswordValidation } from \"better-auth-ui\"\r\nimport { PasswordInput } from \"@/components/password-input\"\r\nimport { CardContent } from \"@/components/ui/card\"\r\nimport {\r\n    Form,\r\n    FormControl,\r\n    FormField,\r\n    FormItem,\r\n    FormLabel,\r\n    FormMessage\r\n} from \"@/components/ui/form\"\r\nimport {\r\n    SettingsCard,\r\n    type SettingsCardClassNames\r\n} from \"../shared/settings-card\"\r\nimport { InputFieldSkeleton } from \"../skeletons/input-field-skeleton\"\r\n\r\nexport interface ChangePasswordCardProps {\r\n    className?: string\r\n    classNames?: SettingsCardClassNames\r\n    accounts?: { providerId: string }[] | null\r\n    isPending?: boolean\r\n    localization?: AuthLocalization\r\n    skipHook?: boolean\r\n    passwordValidation?: PasswordValidation\r\n}\r\n\r\nexport function ChangePasswordCard({\r\n    className,\r\n    classNames,\r\n    accounts,\r\n    isPending,\r\n    localization,\r\n    skipHook,\r\n    passwordValidation\r\n}: ChangePasswordCardProps) {\r\n    const {\r\n        authClient,\r\n        basePath,\r\n        baseURL,\r\n        credentials,\r\n        hooks: { useSession, useListAccounts },\r\n        localization: contextLocalization,\r\n        viewPaths,\r\n        toast\r\n    } = useContext(AuthUIContext)\r\n\r\n    const confirmPasswordEnabled = credentials?.confirmPassword\r\n    const contextPasswordValidation = credentials?.passwordValidation\r\n\r\n    localization = { ...contextLocalization, ...localization }\r\n    passwordValidation = { ...contextPasswordValidation, ...passwordValidation }\r\n\r\n    const { data: sessionData } = useSession()\r\n\r\n    if (!skipHook) {\r\n        const result = useListAccounts()\r\n        accounts = result.data\r\n        isPending = result.isPending\r\n    }\r\n\r\n    const formSchema = z\r\n        .object({\r\n            currentPassword: getPasswordSchema(\r\n                passwordValidation,\r\n                localization\r\n            ),\r\n            newPassword: getPasswordSchema(passwordValidation, {\r\n                PASSWORD_REQUIRED: localization.NEW_PASSWORD_REQUIRED,\r\n                PASSWORD_TOO_SHORT: localization.PASSWORD_TOO_SHORT,\r\n                PASSWORD_TOO_LONG: localization.PASSWORD_TOO_LONG,\r\n                INVALID_PASSWORD: localization.INVALID_PASSWORD\r\n            }),\r\n            confirmPassword: confirmPasswordEnabled\r\n                ? getPasswordSchema(passwordValidation, {\r\n                      PASSWORD_REQUIRED: localization.CONFIRM_PASSWORD_REQUIRED,\r\n                      PASSWORD_TOO_SHORT: localization.PASSWORD_TOO_SHORT,\r\n                      PASSWORD_TOO_LONG: localization.PASSWORD_TOO_LONG,\r\n                      INVALID_PASSWORD: localization.INVALID_PASSWORD\r\n                  })\r\n                : z.string().optional()\r\n        })\r\n        .refine(\r\n            (data) =>\r\n                !confirmPasswordEnabled ||\r\n                data.newPassword === data.confirmPassword,\r\n            {\r\n                message: localization.PASSWORDS_DO_NOT_MATCH,\r\n                path: [\"confirmPassword\"]\r\n            }\r\n        )\r\n\r\n    const form = useForm({\r\n        resolver: zodResolver(formSchema),\r\n        defaultValues: {\r\n            currentPassword: \"\",\r\n            newPassword: \"\",\r\n            confirmPassword: \"\"\r\n        }\r\n    })\r\n\r\n    const setPasswordForm = useForm()\r\n\r\n    const { isSubmitting } = form.formState\r\n\r\n    const setPassword = async () => {\r\n        if (!sessionData) return\r\n        const email = sessionData?.user.email\r\n\r\n        try {\r\n            await authClient.requestPasswordReset({\r\n                email,\r\n                redirectTo: `${baseURL}${basePath}/${viewPaths.RESET_PASSWORD}`,\r\n                fetchOptions: { throw: true }\r\n            })\r\n\r\n            toast({\r\n                variant: \"success\",\r\n                message: localization.FORGOT_PASSWORD_EMAIL!\r\n            })\r\n        } catch (error) {\r\n            toast({\r\n                variant: \"error\",\r\n                message: getLocalizedError({ error, localization })\r\n            })\r\n        }\r\n    }\r\n\r\n    const changePassword = async ({\r\n        currentPassword,\r\n        newPassword\r\n    }: z.infer<typeof formSchema>) => {\r\n        try {\r\n            await authClient.changePassword({\r\n                currentPassword,\r\n                newPassword,\r\n                revokeOtherSessions: true,\r\n                fetchOptions: { throw: true }\r\n            })\r\n\r\n            toast({\r\n                variant: \"success\",\r\n                message: localization.CHANGE_PASSWORD_SUCCESS!\r\n            })\r\n        } catch (error) {\r\n            toast({\r\n                variant: \"error\",\r\n                message: getLocalizedError({ error, localization })\r\n            })\r\n        }\r\n\r\n        form.reset()\r\n    }\r\n\r\n    const credentialsLinked = accounts?.some(\r\n        (acc) => acc.providerId === \"credential\"\r\n    )\r\n\r\n    if (!isPending && !credentialsLinked) {\r\n        return (\r\n            <Form {...setPasswordForm}>\r\n                <form onSubmit={setPasswordForm.handleSubmit(setPassword)}>\r\n                    <SettingsCard\r\n                        title={localization.SET_PASSWORD}\r\n                        description={localization.SET_PASSWORD_DESCRIPTION}\r\n                        actionLabel={localization.SET_PASSWORD}\r\n                        isPending={isPending}\r\n                        className={className}\r\n                        classNames={classNames}\r\n                    />\r\n                </form>\r\n            </Form>\r\n        )\r\n    }\r\n\r\n    return (\r\n        <Form {...form}>\r\n            <form onSubmit={form.handleSubmit(changePassword)}>\r\n                <SettingsCard\r\n                    className={className}\r\n                    classNames={classNames}\r\n                    actionLabel={localization.SAVE}\r\n                    description={localization.CHANGE_PASSWORD_DESCRIPTION}\r\n                    instructions={localization.CHANGE_PASSWORD_INSTRUCTIONS}\r\n                    isPending={isPending}\r\n                    title={localization.CHANGE_PASSWORD}\r\n                >\r\n                    <CardContent\r\n                        className={cn(\"grid gap-6\", classNames?.content)}\r\n                    >\r\n                        {isPending || !accounts ? (\r\n                            <>\r\n                                <InputFieldSkeleton classNames={classNames} />\r\n                                <InputFieldSkeleton classNames={classNames} />\r\n\r\n                                {confirmPasswordEnabled && (\r\n                                    <InputFieldSkeleton\r\n                                        classNames={classNames}\r\n                                    />\r\n                                )}\r\n                            </>\r\n                        ) : (\r\n                            <>\r\n                                <FormField\r\n                                    control={form.control}\r\n                                    name=\"currentPassword\"\r\n                                    render={({ field }) => (\r\n                                        <FormItem>\r\n                                            <FormLabel\r\n                                                className={classNames?.label}\r\n                                            >\r\n                                                {localization.CURRENT_PASSWORD}\r\n                                            </FormLabel>\r\n\r\n                                            <FormControl>\r\n                                                <PasswordInput\r\n                                                    className={\r\n                                                        classNames?.input\r\n                                                    }\r\n                                                    autoComplete=\"current-password\"\r\n                                                    placeholder={\r\n                                                        localization.CURRENT_PASSWORD_PLACEHOLDER\r\n                                                    }\r\n                                                    disabled={isSubmitting}\r\n                                                    {...field}\r\n                                                />\r\n                                            </FormControl>\r\n\r\n                                            <FormMessage\r\n                                                className={classNames?.error}\r\n                                            />\r\n                                        </FormItem>\r\n                                    )}\r\n                                />\r\n\r\n                                <FormField\r\n                                    control={form.control}\r\n                                    name=\"newPassword\"\r\n                                    render={({ field }) => (\r\n                                        <FormItem>\r\n                                            <FormLabel\r\n                                                className={classNames?.label}\r\n                                            >\r\n                                                {localization.NEW_PASSWORD}\r\n                                            </FormLabel>\r\n\r\n                                            <FormControl>\r\n                                                <PasswordInput\r\n                                                    className={\r\n                                                        classNames?.input\r\n                                                    }\r\n                                                    autoComplete=\"new-password\"\r\n                                                    disabled={isSubmitting}\r\n                                                    placeholder={\r\n                                                        localization.NEW_PASSWORD_PLACEHOLDER\r\n                                                    }\r\n                                                    enableToggle\r\n                                                    {...field}\r\n                                                />\r\n                                            </FormControl>\r\n\r\n                                            <FormMessage\r\n                                                className={classNames?.error}\r\n                                            />\r\n                                        </FormItem>\r\n                                    )}\r\n                                />\r\n\r\n                                {confirmPasswordEnabled && (\r\n                                    <FormField\r\n                                        control={form.control}\r\n                                        name=\"confirmPassword\"\r\n                                        render={({ field }) => (\r\n                                            <FormItem>\r\n                                                <FormLabel\r\n                                                    className={\r\n                                                        classNames?.label\r\n                                                    }\r\n                                                >\r\n                                                    {\r\n                                                        localization.CONFIRM_PASSWORD\r\n                                                    }\r\n                                                </FormLabel>\r\n\r\n                                                <FormControl>\r\n                                                    <PasswordInput\r\n                                                        className={\r\n                                                            classNames?.input\r\n                                                        }\r\n                                                        autoComplete=\"new-password\"\r\n                                                        placeholder={\r\n                                                            localization.CONFIRM_PASSWORD_PLACEHOLDER\r\n                                                        }\r\n                                                        disabled={isSubmitting}\r\n                                                        enableToggle\r\n                                                        {...field}\r\n                                                    />\r\n                                                </FormControl>\r\n\r\n                                                <FormMessage\r\n                                                    className={\r\n                                                        classNames?.error\r\n                                                    }\r\n                                                />\r\n                                            </FormItem>\r\n                                        )}\r\n                                    />\r\n                                )}\r\n                            </>\r\n                        )}\r\n                    </CardContent>\r\n                </SettingsCard>\r\n            </form>\r\n        </Form>\r\n    )\r\n}\r\n",
      "type": "registry:component",
      "target": "components/settings/security/change-password-card.tsx"
    },
    {
      "path": "registry/source/settings/account/delete-account-card.tsx",
      "content": "\"use client\"\r\n\r\nimport type { Account } from \"better-auth\"\r\nimport { useContext, useState } from \"react\"\r\nimport { AuthUIContext } from \"better-auth-ui\"\r\nimport type { AuthLocalization } from \"better-auth-ui\"\r\nimport type { SettingsCardClassNames } from \"../shared/settings-card\"\r\nimport { SettingsCard } from \"../shared/settings-card\"\r\nimport { DeleteAccountDialog } from \"./delete-account-dialog\"\r\n\r\nexport interface DeleteAccountCardProps {\r\n    className?: string\r\n    classNames?: SettingsCardClassNames\r\n    accounts?: Account[] | null\r\n    isPending?: boolean\r\n    localization?: AuthLocalization\r\n    skipHook?: boolean\r\n}\r\n\r\nexport function DeleteAccountCard({\r\n    className,\r\n    classNames,\r\n    accounts,\r\n    isPending,\r\n    localization,\r\n    skipHook\r\n}: DeleteAccountCardProps) {\r\n    const {\r\n        hooks: { useListAccounts },\r\n        localization: contextLocalization\r\n    } = useContext(AuthUIContext)\r\n\r\n    localization = { ...contextLocalization, ...localization }\r\n\r\n    const [showDialog, setShowDialog] = useState(false)\r\n\r\n    if (!skipHook) {\r\n        const result = useListAccounts()\r\n        accounts = result.data\r\n        isPending = result.isPending\r\n    }\r\n\r\n    return (\r\n        <div>\r\n            <SettingsCard\r\n                className={className}\r\n                classNames={classNames}\r\n                actionLabel={localization?.DELETE_ACCOUNT}\r\n                description={localization?.DELETE_ACCOUNT_DESCRIPTION}\r\n                isPending={isPending}\r\n                title={localization?.DELETE_ACCOUNT}\r\n                variant=\"destructive\"\r\n                action={() => setShowDialog(true)}\r\n            />\r\n\r\n            <DeleteAccountDialog\r\n                classNames={classNames}\r\n                accounts={accounts}\r\n                localization={localization}\r\n                open={showDialog}\r\n                onOpenChange={setShowDialog}\r\n            />\r\n        </div>\r\n    )\r\n}\r\n",
      "type": "registry:component",
      "target": "components/settings/account/delete-account-card.tsx"
    },
    {
      "path": "registry/source/settings/providers/providers-card.tsx",
      "content": "\"use client\"\r\n\r\nimport type { Account } from \"better-auth\"\r\nimport { useContext } from \"react\"\r\nimport { AuthUIContext } from \"better-auth-ui\"\r\nimport { socialProviders } from \"better-auth-ui\"\r\nimport { cn } from \"better-auth-ui\"\r\nimport type { AuthLocalization } from \"better-auth-ui\"\r\nimport type { Refetch } from \"better-auth-ui\"\r\nimport { CardContent } from \"@/components/ui/card\"\r\nimport type { SettingsCardClassNames } from \"../shared/settings-card\"\r\nimport { SettingsCard } from \"../shared/settings-card\"\r\nimport { SettingsCellSkeleton } from \"../skeletons/settings-cell-skeleton\"\r\nimport { ProviderCell } from \"./provider-cell\"\r\n\r\nexport interface ProvidersCardProps {\r\n    className?: string\r\n    classNames?: SettingsCardClassNames\r\n    accounts?: Account[] | null\r\n    isPending?: boolean\r\n    localization?: Partial<AuthLocalization>\r\n    skipHook?: boolean\r\n    refetch?: Refetch\r\n}\r\n\r\nexport function ProvidersCard({\r\n    className,\r\n    classNames,\r\n    accounts,\r\n    isPending,\r\n    localization,\r\n    skipHook,\r\n    refetch\r\n}: ProvidersCardProps) {\r\n    const {\r\n        hooks: { useListAccounts },\r\n        localization: contextLocalization,\r\n        social,\r\n        genericOAuth\r\n    } = useContext(AuthUIContext)\r\n\r\n    localization = { ...contextLocalization, ...localization }\r\n\r\n    if (!skipHook) {\r\n        const result = useListAccounts()\r\n        accounts = result.data\r\n        isPending = result.isPending\r\n        refetch = result.refetch\r\n    }\r\n\r\n    return (\r\n        <SettingsCard\r\n            className={className}\r\n            classNames={classNames}\r\n            title={localization.PROVIDERS}\r\n            description={localization.PROVIDERS_DESCRIPTION}\r\n            isPending={isPending}\r\n        >\r\n            <CardContent className={cn(\"grid gap-4\", classNames?.content)}>\r\n                {isPending ? (\r\n                    social?.providers?.map((provider) => (\r\n                        <SettingsCellSkeleton\r\n                            key={provider}\r\n                            classNames={classNames}\r\n                        />\r\n                    ))\r\n                ) : (\r\n                    <>\r\n                        {social?.providers?.map((provider) => {\r\n                            const socialProvider = socialProviders.find(\r\n                                (socialProvider) =>\r\n                                    socialProvider.provider === provider\r\n                            )\r\n\r\n                            if (!socialProvider) return null\r\n\r\n                            return (\r\n                                <ProviderCell\r\n                                    key={provider}\r\n                                    classNames={classNames}\r\n                                    account={accounts?.find(\r\n                                        (acc) => acc.providerId === provider\r\n                                    )}\r\n                                    provider={socialProvider}\r\n                                    refetch={refetch}\r\n                                />\r\n                            )\r\n                        })}\r\n\r\n                        {genericOAuth?.providers?.map((provider) => (\r\n                            <ProviderCell\r\n                                key={provider.provider}\r\n                                classNames={classNames}\r\n                                account={accounts?.find(\r\n                                    (acc) =>\r\n                                        acc.providerId === provider.provider\r\n                                )}\r\n                                provider={provider}\r\n                                refetch={refetch}\r\n                                other\r\n                            />\r\n                        ))}\r\n                    </>\r\n                )}\r\n            </CardContent>\r\n        </SettingsCard>\r\n    )\r\n}\r\n",
      "type": "registry:component",
      "target": "components/settings/providers/providers-card.tsx"
    },
    {
      "path": "registry/source/settings/security/sessions-card.tsx",
      "content": "\"use client\"\r\nimport { useContext } from \"react\"\r\n\r\nimport { AuthUIContext } from \"better-auth-ui\"\r\nimport { cn } from \"better-auth-ui\"\r\nimport type { AuthLocalization } from \"better-auth-ui\"\r\nimport { CardContent } from \"@/components/ui/card\"\r\nimport type { SettingsCardClassNames } from \"../shared/settings-card\"\r\nimport { SettingsCard } from \"../shared/settings-card\"\r\nimport { SettingsCellSkeleton } from \"../skeletons/settings-cell-skeleton\"\r\nimport { SessionCell } from \"./session-cell\"\r\n\r\nexport interface SessionsCardProps {\r\n    className?: string\r\n    classNames?: SettingsCardClassNames\r\n    localization?: Partial<AuthLocalization>\r\n}\r\n\r\nexport function SessionsCard({\r\n    className,\r\n    classNames,\r\n    localization\r\n}: SessionsCardProps) {\r\n    const {\r\n        hooks: { useListSessions },\r\n        localization: contextLocalization\r\n    } = useContext(AuthUIContext)\r\n\r\n    localization = { ...contextLocalization, ...localization }\r\n\r\n    const { data: sessions, isPending, refetch } = useListSessions()\r\n\r\n    return (\r\n        <SettingsCard\r\n            className={className}\r\n            classNames={classNames}\r\n            description={localization.SESSIONS_DESCRIPTION}\r\n            isPending={isPending}\r\n            title={localization.SESSIONS}\r\n        >\r\n            <CardContent className={cn(\"grid gap-4\", classNames?.content)}>\r\n                {isPending ? (\r\n                    <SettingsCellSkeleton classNames={classNames} />\r\n                ) : (\r\n                    sessions?.map((session) => (\r\n                        <SessionCell\r\n                            key={session.id}\r\n                            classNames={classNames}\r\n                            localization={localization}\r\n                            session={session}\r\n                            refetch={refetch}\r\n                        />\r\n                    ))\r\n                )}\r\n            </CardContent>\r\n        </SettingsCard>\r\n    )\r\n}\r\n",
      "type": "registry:component",
      "target": "components/settings/security/sessions-card.tsx"
    },
    {
      "path": "registry/source/settings/two-factor/two-factor-card.tsx",
      "content": "\"use client\"\r\n\r\nimport { useContext, useState } from \"react\"\r\nimport { AuthUIContext } from \"better-auth-ui\"\r\nimport type { AuthLocalization } from \"better-auth-ui\"\r\nimport type { User } from \"better-auth-ui\"\r\nimport type { SettingsCardClassNames } from \"../shared/settings-card\"\r\nimport { SettingsCard } from \"../shared/settings-card\"\r\nimport { TwoFactorPasswordDialog } from \"./two-factor-password-dialog\"\r\n\r\nexport interface TwoFactorCardProps {\r\n    className?: string\r\n    classNames?: SettingsCardClassNames\r\n    localization?: AuthLocalization\r\n}\r\n\r\nexport function TwoFactorCard({\r\n    className,\r\n    classNames,\r\n    localization\r\n}: TwoFactorCardProps) {\r\n    const {\r\n        localization: contextLocalization,\r\n        hooks: { useSession }\r\n    } = useContext(AuthUIContext)\r\n\r\n    const [showPasswordDialog, setShowPasswordDialog] = useState(false)\r\n\r\n    localization = { ...contextLocalization, ...localization }\r\n\r\n    const { data: sessionData, isPending } = useSession()\r\n    const isTwoFactorEnabled = (sessionData?.user as User)?.twoFactorEnabled\r\n\r\n    return (\r\n        <div>\r\n            <SettingsCard\r\n                className={className}\r\n                classNames={classNames}\r\n                actionLabel={\r\n                    isTwoFactorEnabled\r\n                        ? localization.DISABLE_TWO_FACTOR\r\n                        : localization.ENABLE_TWO_FACTOR\r\n                }\r\n                description={localization.TWO_FACTOR_CARD_DESCRIPTION}\r\n                instructions={\r\n                    isTwoFactorEnabled\r\n                        ? localization.TWO_FACTOR_DISABLE_INSTRUCTIONS\r\n                        : localization.TWO_FACTOR_ENABLE_INSTRUCTIONS\r\n                }\r\n                isPending={isPending}\r\n                title={localization.TWO_FACTOR}\r\n                action={() => setShowPasswordDialog(true)}\r\n            />\r\n\r\n            <TwoFactorPasswordDialog\r\n                classNames={classNames}\r\n                open={showPasswordDialog}\r\n                onOpenChange={setShowPasswordDialog}\r\n                isTwoFactorEnabled={!!isTwoFactorEnabled}\r\n            />\r\n        </div>\r\n    )\r\n}\r\n",
      "type": "registry:component",
      "target": "components/settings/two-factor/two-factor-card.tsx"
    },
    {
      "path": "registry/source/settings/passkey/passkeys-card.tsx",
      "content": "\"use client\"\r\n\r\nimport { useContext, useState } from \"react\"\r\nimport { useForm } from \"react-hook-form\"\r\n\r\nimport { AuthUIContext } from \"better-auth-ui\"\r\nimport { cn, getLocalizedError } from \"better-auth-ui\"\r\nimport type { AuthLocalization } from \"better-auth-ui\"\r\nimport { CardContent } from \"@/components/ui/card\"\r\nimport { Form } from \"@/components/ui/form\"\r\nimport { SessionFreshnessDialog } from \"../shared/session-freshness-dialog\"\r\nimport type { SettingsCardClassNames } from \"../shared/settings-card\"\r\nimport { SettingsCard } from \"../shared/settings-card\"\r\nimport { PasskeyCell } from \"./passkey-cell\"\r\n\r\nexport interface PasskeysCardProps {\r\n    className?: string\r\n    classNames?: SettingsCardClassNames\r\n    localization?: AuthLocalization\r\n}\r\n\r\nexport function PasskeysCard({\r\n    className,\r\n    classNames,\r\n    localization\r\n}: PasskeysCardProps) {\r\n    const {\r\n        authClient,\r\n        freshAge,\r\n        hooks: { useListPasskeys, useSession },\r\n        localization: authLocalization,\r\n        toast\r\n    } = useContext(AuthUIContext)\r\n\r\n    localization = { ...authLocalization, ...localization }\r\n\r\n    const { data: passkeys, isPending, refetch } = useListPasskeys()\r\n\r\n    const { data: sessionData } = useSession()\r\n    const session = sessionData?.session\r\n    const isFresh = session\r\n        ? Date.now() - new Date(session?.createdAt).getTime() < freshAge * 1000\r\n        : false\r\n\r\n    const [showFreshnessDialog, setShowFreshnessDialog] = useState(false)\r\n\r\n    const addPasskey = async () => {\r\n        // If session isn't fresh, show the freshness dialog\r\n        if (!isFresh) {\r\n            setShowFreshnessDialog(true)\r\n            return\r\n        }\r\n\r\n        try {\r\n            await authClient.passkey.addPasskey({\r\n                fetchOptions: { throw: true }\r\n            })\r\n            await refetch?.()\r\n        } catch (error) {\r\n            toast({\r\n                variant: \"error\",\r\n                message: getLocalizedError({ error, localization })\r\n            })\r\n        }\r\n    }\r\n\r\n    const form = useForm()\r\n\r\n    return (\r\n        <>\r\n            <SessionFreshnessDialog\r\n                open={showFreshnessDialog}\r\n                onOpenChange={setShowFreshnessDialog}\r\n                classNames={classNames}\r\n                localization={localization}\r\n            />\r\n\r\n            <Form {...form}>\r\n                <form onSubmit={form.handleSubmit(addPasskey)}>\r\n                    <SettingsCard\r\n                        className={className}\r\n                        classNames={classNames}\r\n                        actionLabel={localization.ADD_PASSKEY}\r\n                        description={localization.PASSKEYS_DESCRIPTION}\r\n                        instructions={localization.PASSKEYS_INSTRUCTIONS}\r\n                        isPending={isPending}\r\n                        title={localization.PASSKEYS}\r\n                    >\r\n                        {passkeys && passkeys.length > 0 && (\r\n                            <CardContent\r\n                                className={cn(\r\n                                    \"grid gap-4\",\r\n                                    classNames?.content\r\n                                )}\r\n                            >\r\n                                {passkeys?.map((passkey) => (\r\n                                    <PasskeyCell\r\n                                        key={passkey.id}\r\n                                        classNames={classNames}\r\n                                        localization={localization}\r\n                                        passkey={passkey}\r\n                                    />\r\n                                ))}\r\n                            </CardContent>\r\n                        )}\r\n                    </SettingsCard>\r\n                </form>\r\n            </Form>\r\n        </>\r\n    )\r\n}\r\n",
      "type": "registry:component",
      "target": "components/settings/passkey/passkeys-card.tsx"
    },
    {
      "path": "registry/source/settings/account/update-avatar-card.tsx",
      "content": "\"use client\"\r\n\r\nimport { Trash2Icon, UploadCloudIcon } from \"lucide-react\"\r\nimport { type ComponentProps, useContext, useRef, useState } from \"react\"\r\n\r\nimport { AuthUIContext } from \"better-auth-ui\"\r\nimport { fileToBase64, resizeAndCropImage } from \"better-auth-ui\"\r\nimport { cn, getLocalizedError } from \"better-auth-ui\"\r\nimport type { AuthLocalization } from \"better-auth-ui\"\r\nimport { Button } from \"@/components/ui/button\"\r\nimport { Card } from \"@/components/ui/card\"\r\nimport {\r\n    DropdownMenu,\r\n    DropdownMenuContent,\r\n    DropdownMenuItem,\r\n    DropdownMenuTrigger\r\n} from \"@/components/ui/dropdown-menu\"\r\nimport { UserAvatar } from \"@/components/user-avatar\"\r\nimport type { SettingsCardClassNames } from \"../shared/settings-card\"\r\nimport { SettingsCardFooter } from \"../shared/settings-card-footer\"\r\nimport { SettingsCardHeader } from \"../shared/settings-card-header\"\r\n\r\nexport interface UpdateAvatarCardProps extends ComponentProps<typeof Card> {\r\n    className?: string\r\n    classNames?: SettingsCardClassNames\r\n    localization?: AuthLocalization\r\n}\r\n\r\nexport function UpdateAvatarCard({\r\n    className,\r\n    classNames,\r\n    localization,\r\n    ...props\r\n}: UpdateAvatarCardProps) {\r\n    const {\r\n        hooks: { useSession },\r\n        mutators: { updateUser },\r\n        localization: authLocalization,\r\n        optimistic,\r\n        avatar,\r\n        toast\r\n    } = useContext(AuthUIContext)\r\n\r\n    localization = { ...authLocalization, ...localization }\r\n\r\n    const { data: sessionData, isPending, refetch } = useSession()\r\n    const fileInputRef = useRef<HTMLInputElement | null>(null)\r\n    const [loading, setLoading] = useState(false)\r\n\r\n    const handleAvatarChange = async (file: File) => {\r\n        if (!sessionData || !avatar) return\r\n\r\n        setLoading(true)\r\n        const resizedFile = await resizeAndCropImage(\r\n            file,\r\n            crypto.randomUUID(),\r\n            avatar.size,\r\n            avatar.extension\r\n        )\r\n\r\n        let image: string | undefined | null\r\n\r\n        if (avatar.upload) {\r\n            image = await avatar.upload(resizedFile)\r\n        } else {\r\n            image = await fileToBase64(resizedFile)\r\n        }\r\n\r\n        if (!image) {\r\n            setLoading(false)\r\n            return\r\n        }\r\n\r\n        if (optimistic && !avatar.upload) setLoading(false)\r\n\r\n        try {\r\n            await updateUser({ image })\r\n            await refetch?.()\r\n        } catch (error) {\r\n            toast({\r\n                variant: \"error\",\r\n                message: getLocalizedError({ error, localization })\r\n            })\r\n        }\r\n\r\n        setLoading(false)\r\n    }\r\n\r\n    const handleDeleteAvatar = async () => {\r\n        if (!sessionData) return\r\n\r\n        setLoading(true)\r\n\r\n        try {\r\n            // If a custom storage remover is provided, attempt to clean up the old asset first\r\n            if (sessionData.user.image && avatar?.delete) {\r\n                await avatar.delete(sessionData.user.image)\r\n            }\r\n\r\n            await updateUser({ image: null })\r\n            await refetch?.()\r\n        } catch (error) {\r\n            toast({\r\n                variant: \"error\",\r\n                message: getLocalizedError({ error, localization })\r\n            })\r\n        }\r\n\r\n        setLoading(false)\r\n    }\r\n\r\n    const openFileDialog = () => fileInputRef.current?.click()\r\n\r\n    return (\r\n        <Card\r\n            className={cn(\r\n                \"w-full pb-0 text-start\",\r\n                className,\r\n                classNames?.base\r\n            )}\r\n            {...props}\r\n        >\r\n            <input\r\n                ref={fileInputRef}\r\n                accept=\"image/*\"\r\n                disabled={loading}\r\n                hidden\r\n                type=\"file\"\r\n                onChange={(e) => {\r\n                    const file = e.target.files?.item(0)\r\n                    if (file) handleAvatarChange(file)\r\n\r\n                    e.target.value = \"\"\r\n                }}\r\n            />\r\n\r\n            <div className=\"flex justify-between\">\r\n                <SettingsCardHeader\r\n                    className=\"grow self-start\"\r\n                    title={localization.AVATAR}\r\n                    description={localization.AVATAR_DESCRIPTION}\r\n                    isPending={isPending}\r\n                    classNames={classNames}\r\n                />\r\n\r\n                <DropdownMenu>\r\n                    <DropdownMenuTrigger asChild>\r\n                        <Button\r\n                            className=\"me-6 size-fit rounded-full\"\r\n                            size=\"icon\"\r\n                            variant=\"ghost\"\r\n                        >\r\n                            <UserAvatar\r\n                                isPending={isPending || loading}\r\n                                key={sessionData?.user.image}\r\n                                className=\"size-20 text-2xl\"\r\n                                classNames={classNames?.avatar}\r\n                                user={sessionData?.user}\r\n                                localization={localization}\r\n                            />\r\n                        </Button>\r\n                    </DropdownMenuTrigger>\r\n\r\n                    <DropdownMenuContent\r\n                        align=\"end\"\r\n                        onCloseAutoFocus={(e) => e.preventDefault()}\r\n                    >\r\n                        <DropdownMenuItem\r\n                            onClick={openFileDialog}\r\n                            disabled={loading}\r\n                        >\r\n                            <UploadCloudIcon />\r\n                            {localization.UPLOAD_AVATAR}\r\n                        </DropdownMenuItem>\r\n                        {sessionData?.user.image && (\r\n                            <DropdownMenuItem\r\n                                onClick={handleDeleteAvatar}\r\n                                disabled={loading}\r\n                                variant=\"destructive\"\r\n                            >\r\n                                <Trash2Icon />\r\n                                {localization.DELETE_AVATAR}\r\n                            </DropdownMenuItem>\r\n                        )}\r\n                    </DropdownMenuContent>\r\n                </DropdownMenu>\r\n            </div>\r\n\r\n            <SettingsCardFooter\r\n                className=\"!py-5\"\r\n                instructions={localization.AVATAR_INSTRUCTIONS}\r\n                classNames={classNames}\r\n                isPending={isPending}\r\n                isSubmitting={loading}\r\n            />\r\n        </Card>\r\n    )\r\n}\r\n",
      "type": "registry:component",
      "target": "components/settings/account/update-avatar-card.tsx"
    },
    {
      "path": "registry/source/settings/account/update-username-card.tsx",
      "content": "\"use client\"\r\n\r\nimport { useContext } from \"react\"\r\nimport { AuthUIContext } from \"better-auth-ui\"\r\nimport type { User } from \"better-auth-ui\"\r\nimport type { SettingsCardProps } from \"../shared/settings-card\"\r\nimport { UpdateFieldCard } from \"./update-field-card\"\r\n\r\nexport type UpdateUsernameCardProps = SettingsCardProps\r\n\r\nexport function UpdateUsernameCard({\r\n    className,\r\n    classNames,\r\n    localization,\r\n    ...props\r\n}: SettingsCardProps) {\r\n    const {\r\n        hooks: { useSession },\r\n        localization: contextLocalization\r\n    } = useContext(AuthUIContext)\r\n\r\n    localization = { ...contextLocalization, ...localization }\r\n\r\n    const { data: sessionData } = useSession()\r\n    const value =\r\n        (sessionData?.user as User)?.displayUsername ||\r\n        (sessionData?.user as User)?.username\r\n\r\n    return (\r\n        <UpdateFieldCard\r\n            className={className}\r\n            classNames={classNames}\r\n            value={value}\r\n            description={localization.USERNAME_DESCRIPTION}\r\n            name=\"username\"\r\n            instructions={localization.USERNAME_INSTRUCTIONS}\r\n            label={localization.USERNAME}\r\n            localization={localization}\r\n            placeholder={localization.USERNAME_PLACEHOLDER}\r\n            required\r\n            {...props}\r\n        />\r\n    )\r\n}\r\n",
      "type": "registry:component",
      "target": "components/settings/account/update-username-card.tsx"
    },
    {
      "path": "registry/source/settings/account/update-name-card.tsx",
      "content": "\"use client\"\r\n\r\nimport { useContext } from \"react\"\r\nimport { AuthUIContext } from \"better-auth-ui\"\r\nimport type { SettingsCardProps } from \"../shared/settings-card\"\r\nimport { UpdateFieldCard } from \"./update-field-card\"\r\n\r\nexport type UpdateNameCardProps = SettingsCardProps\r\n\r\nexport function UpdateNameCard({\r\n    className,\r\n    classNames,\r\n    localization,\r\n    ...props\r\n}: SettingsCardProps) {\r\n    const {\r\n        hooks: { useSession },\r\n        localization: contextLocalization,\r\n        nameRequired\r\n    } = useContext(AuthUIContext)\r\n\r\n    localization = { ...contextLocalization, ...localization }\r\n\r\n    const { data: sessionData } = useSession()\r\n\r\n    return (\r\n        <UpdateFieldCard\r\n            className={className}\r\n            classNames={classNames}\r\n            value={sessionData?.user.name}\r\n            description={localization.NAME_DESCRIPTION}\r\n            name=\"name\"\r\n            instructions={localization.NAME_INSTRUCTIONS}\r\n            label={localization.NAME}\r\n            localization={localization}\r\n            placeholder={localization.NAME_PLACEHOLDER}\r\n            required={nameRequired}\r\n            {...props}\r\n        />\r\n    )\r\n}\r\n",
      "type": "registry:component",
      "target": "components/settings/account/update-name-card.tsx"
    },
    {
      "path": "registry/source/settings/account/update-field-card.tsx",
      "content": "\"use client\"\r\n\r\nimport { zodResolver } from \"@hookform/resolvers/zod\"\r\nimport { type ReactNode, useContext, useMemo } from \"react\"\r\nimport { useForm } from \"react-hook-form\"\r\nimport * as z from \"zod\"\r\n\r\nimport { AuthUIContext } from \"better-auth-ui\"\r\nimport { cn, getLocalizedError } from \"better-auth-ui\"\r\nimport type { AuthLocalization } from \"better-auth-ui\"\r\nimport type { FieldType } from \"better-auth-ui\"\r\nimport { CardContent } from \"@/components/ui/card\"\r\nimport { Checkbox } from \"@/components/ui/checkbox\"\r\nimport {\r\n    Form,\r\n    FormControl,\r\n    FormField,\r\n    FormItem,\r\n    FormLabel,\r\n    FormMessage\r\n} from \"@/components/ui/form\"\r\nimport { Input } from \"@/components/ui/input\"\r\nimport { Skeleton } from \"@/components/ui/skeleton\"\r\nimport { Textarea } from \"@/components/ui/textarea\"\r\nimport {\r\n    SettingsCard,\r\n    type SettingsCardClassNames\r\n} from \"../shared/settings-card\"\r\n\r\nexport interface UpdateFieldCardProps {\r\n    className?: string\r\n    classNames?: SettingsCardClassNames\r\n    description?: ReactNode\r\n    instructions?: ReactNode\r\n    localization?: Partial<AuthLocalization>\r\n    name: string\r\n    placeholder?: string\r\n    required?: boolean\r\n    label?: ReactNode\r\n    type?: FieldType\r\n    multiline?: boolean\r\n    value?: unknown\r\n    validate?: (value: string) => boolean | Promise<boolean>\r\n}\r\n\r\nexport function UpdateFieldCard({\r\n    className,\r\n    classNames,\r\n    description,\r\n    instructions,\r\n    localization: localizationProp,\r\n    name,\r\n    placeholder,\r\n    required,\r\n    label,\r\n    type,\r\n    multiline,\r\n    value,\r\n    validate\r\n}: UpdateFieldCardProps) {\r\n    const {\r\n        hooks: { useSession },\r\n        mutators: { updateUser },\r\n        localization: contextLocalization,\r\n        optimistic,\r\n        toast\r\n    } = useContext(AuthUIContext)\r\n\r\n    const localization = useMemo(\r\n        () => ({ ...contextLocalization, ...localizationProp }),\r\n        [contextLocalization, localizationProp]\r\n    )\r\n\r\n    const { isPending } = useSession()\r\n\r\n    let fieldSchema = z.unknown() as z.ZodType<unknown>\r\n\r\n    // Create the appropriate schema based on type\r\n    if (type === \"number\") {\r\n        fieldSchema = required\r\n            ? z.preprocess(\r\n                  (val) => (!val ? undefined : Number(val)),\r\n                  z.number({\r\n                      message: `${label} ${localization.IS_INVALID}`\r\n                  })\r\n              )\r\n            : z.coerce\r\n                  .number({\r\n                      message: `${label} ${localization.IS_INVALID}`\r\n                  })\r\n                  .optional()\r\n    } else if (type === \"boolean\") {\r\n        fieldSchema = required\r\n            ? z.coerce\r\n                  .boolean({\r\n                      message: `${label} ${localization.IS_INVALID}`\r\n                  })\r\n                  .refine((val) => val === true, {\r\n                      message: `${label} ${localization.IS_REQUIRED}`\r\n                  })\r\n            : z.coerce.boolean({\r\n                  message: `${label} ${localization.IS_INVALID}`\r\n              })\r\n    } else {\r\n        fieldSchema = required\r\n            ? z.string().min(1, `${label} ${localization.IS_REQUIRED}`)\r\n            : z.string().optional()\r\n    }\r\n\r\n    const form = useForm({\r\n        resolver: zodResolver(z.object({ [name]: fieldSchema })),\r\n        values: { [name]: value || \"\" }\r\n    })\r\n\r\n    const { isSubmitting } = form.formState\r\n\r\n    const updateField = async (values: Record<string, unknown>) => {\r\n        await new Promise((resolve) => setTimeout(resolve))\r\n        const newValue = values[name]\r\n\r\n        if (value === newValue) {\r\n            toast({\r\n                variant: \"error\",\r\n                message: `${label} ${localization.IS_THE_SAME}`\r\n            })\r\n            return\r\n        }\r\n\r\n        if (\r\n            validate &&\r\n            typeof newValue === \"string\" &&\r\n            !(await validate(newValue))\r\n        ) {\r\n            form.setError(name, {\r\n                message: `${label} ${localization.IS_INVALID}`\r\n            })\r\n\r\n            return\r\n        }\r\n\r\n        try {\r\n            await updateUser({ [name]: newValue })\r\n\r\n            toast({\r\n                variant: \"success\",\r\n                message: `${label} ${localization.UPDATED_SUCCESSFULLY}`\r\n            })\r\n        } catch (error) {\r\n            toast({\r\n                variant: \"error\",\r\n                message: getLocalizedError({ error, localization })\r\n            })\r\n        }\r\n    }\r\n\r\n    return (\r\n        <Form {...form}>\r\n            <form onSubmit={form.handleSubmit(updateField)}>\r\n                <SettingsCard\r\n                    className={className}\r\n                    classNames={classNames}\r\n                    description={description}\r\n                    instructions={instructions}\r\n                    isPending={isPending}\r\n                    title={label}\r\n                    actionLabel={localization.SAVE}\r\n                    optimistic={optimistic}\r\n                >\r\n                    <CardContent className={classNames?.content}>\r\n                        {type === \"boolean\" ? (\r\n                            <FormField\r\n                                control={form.control}\r\n                                name={name}\r\n                                render={({ field }) => (\r\n                                    <FormItem className=\"flex\">\r\n                                        <FormControl>\r\n                                            <Checkbox\r\n                                                checked={field.value as boolean}\r\n                                                onCheckedChange={field.onChange}\r\n                                                disabled={isSubmitting}\r\n                                                className={classNames?.checkbox}\r\n                                            />\r\n                                        </FormControl>\r\n\r\n                                        <FormLabel\r\n                                            className={classNames?.label}\r\n                                        >\r\n                                            {label}\r\n                                        </FormLabel>\r\n\r\n                                        <FormMessage\r\n                                            className={classNames?.error}\r\n                                        />\r\n                                    </FormItem>\r\n                                )}\r\n                            />\r\n                        ) : isPending ? (\r\n                            <Skeleton\r\n                                className={cn(\r\n                                    \"h-9 w-full\",\r\n                                    classNames?.skeleton\r\n                                )}\r\n                            />\r\n                        ) : (\r\n                            <FormField\r\n                                control={form.control}\r\n                                name={name}\r\n                                render={({ field }) => (\r\n                                    <FormItem>\r\n                                        <FormControl>\r\n                                            {type === \"number\" ? (\r\n                                                <Input\r\n                                                    className={\r\n                                                        classNames?.input\r\n                                                    }\r\n                                                    type=\"number\"\r\n                                                    placeholder={\r\n                                                        placeholder ||\r\n                                                        (typeof label ===\r\n                                                        \"string\"\r\n                                                            ? label\r\n                                                            : \"\")\r\n                                                    }\r\n                                                    disabled={isSubmitting}\r\n                                                    {...field}\r\n                                                    value={\r\n                                                        field.value as string\r\n                                                    }\r\n                                                />\r\n                                            ) : multiline ? (\r\n                                                <Textarea\r\n                                                    className={\r\n                                                        classNames?.input\r\n                                                    }\r\n                                                    placeholder={\r\n                                                        placeholder ||\r\n                                                        (typeof label ===\r\n                                                        \"string\"\r\n                                                            ? label\r\n                                                            : \"\")\r\n                                                    }\r\n                                                    disabled={isSubmitting}\r\n                                                    {...field}\r\n                                                    value={\r\n                                                        field.value as string\r\n                                                    }\r\n                                                />\r\n                                            ) : (\r\n                                                <Input\r\n                                                    className={\r\n                                                        classNames?.input\r\n                                                    }\r\n                                                    type=\"text\"\r\n                                                    placeholder={\r\n                                                        placeholder ||\r\n                                                        (typeof label ===\r\n                                                        \"string\"\r\n                                                            ? label\r\n                                                            : \"\")\r\n                                                    }\r\n                                                    disabled={isSubmitting}\r\n                                                    {...field}\r\n                                                    value={\r\n                                                        field.value as string\r\n                                                    }\r\n                                                />\r\n                                            )}\r\n                                        </FormControl>\r\n\r\n                                        <FormMessage\r\n                                            className={classNames?.error}\r\n                                        />\r\n                                    </FormItem>\r\n                                )}\r\n                            />\r\n                        )}\r\n                    </CardContent>\r\n                </SettingsCard>\r\n            </form>\r\n        </Form>\r\n    )\r\n}\r\n",
      "type": "registry:component",
      "target": "components/settings/account/update-field-card.tsx"
    },
    {
      "path": "registry/source/settings/account/accounts-card.tsx",
      "content": "\"use client\"\r\nimport { useContext } from \"react\"\r\n\r\nimport { AuthUIContext } from \"better-auth-ui\"\r\nimport { cn } from \"better-auth-ui\"\r\nimport type { AuthLocalization } from \"better-auth-ui\"\r\nimport { CardContent } from \"@/components/ui/card\"\r\nimport type { SettingsCardClassNames } from \"../shared/settings-card\"\r\nimport { SettingsCard } from \"../shared/settings-card\"\r\nimport { AccountCell } from \"./account-cell\"\r\n\r\nexport interface AccountsCardProps {\r\n    className?: string\r\n    classNames?: SettingsCardClassNames\r\n    localization?: Partial<AuthLocalization>\r\n}\r\n\r\nexport function AccountsCard({\r\n    className,\r\n    classNames,\r\n    localization\r\n}: AccountsCardProps) {\r\n    const {\r\n        basePath,\r\n        hooks: { useListDeviceSessions, useSession },\r\n        localization: contextLocalization,\r\n        viewPaths,\r\n        navigate\r\n    } = useContext(AuthUIContext)\r\n\r\n    localization = { ...contextLocalization, ...localization }\r\n\r\n    const { data: deviceSessions, isPending, refetch } = useListDeviceSessions()\r\n    const { data: sessionData } = useSession()\r\n\r\n    const otherDeviceSessions = (deviceSessions || []).filter(\r\n        (ds) => ds.session.id !== sessionData?.session.id\r\n    )\r\n\r\n    return (\r\n        <SettingsCard\r\n            className={className}\r\n            classNames={classNames}\r\n            title={localization.ACCOUNTS}\r\n            description={localization.ACCOUNTS_DESCRIPTION}\r\n            actionLabel={localization.ADD_ACCOUNT}\r\n            instructions={localization.ACCOUNTS_INSTRUCTIONS}\r\n            isPending={isPending}\r\n            action={() => navigate(`${basePath}/${viewPaths.SIGN_IN}`)}\r\n        >\r\n            {deviceSessions?.length && (\r\n                <CardContent className={cn(\"grid gap-4\", classNames?.content)}>\r\n                    {sessionData && (\r\n                        <AccountCell\r\n                            classNames={classNames}\r\n                            deviceSession={sessionData}\r\n                            localization={localization}\r\n                            refetch={refetch}\r\n                        />\r\n                    )}\r\n\r\n                    {otherDeviceSessions.map((deviceSession) => (\r\n                        <AccountCell\r\n                            key={deviceSession.session.id}\r\n                            classNames={classNames}\r\n                            deviceSession={deviceSession}\r\n                            localization={localization}\r\n                            refetch={refetch}\r\n                        />\r\n                    ))}\r\n                </CardContent>\r\n            )}\r\n        </SettingsCard>\r\n    )\r\n}\r\n",
      "type": "registry:component",
      "target": "components/settings/account/accounts-card.tsx"
    },
    {
      "path": "registry/source/settings/api-key/api-keys-card.tsx",
      "content": "\"use client\"\r\n\r\nimport { useContext, useMemo, useState } from \"react\"\r\nimport { AuthUIContext } from \"better-auth-ui\"\r\nimport { cn } from \"better-auth-ui\"\r\nimport { CardContent } from \"@/components/ui/card\"\r\nimport type { SettingsCardProps } from \"../shared/settings-card\"\r\nimport { SettingsCard } from \"../shared/settings-card\"\r\nimport { ApiKeyCell } from \"./api-key-cell\"\r\nimport { ApiKeyDisplayDialog } from \"./api-key-display-dialog\"\r\nimport { CreateApiKeyDialog } from \"./create-api-key-dialog\"\r\n\r\nexport interface ApiKeysCardProps extends SettingsCardProps {\r\n    organizationId?: string\r\n}\r\n\r\nexport function ApiKeysCard({\r\n    className,\r\n    classNames,\r\n    localization,\r\n    organizationId,\r\n    ...props\r\n}: ApiKeysCardProps) {\r\n    const {\r\n        hooks: { useListApiKeys },\r\n        localization: contextLocalization\r\n    } = useContext(AuthUIContext)\r\n\r\n    localization = { ...contextLocalization, ...localization }\r\n\r\n    const { data: apiKeys, isPending, refetch } = useListApiKeys()\r\n\r\n    // Filter API keys by organizationId\r\n    const filteredApiKeys = useMemo(() => {\r\n        return apiKeys?.filter(\r\n            (apiKey) => organizationId === apiKey.metadata?.organizationId\r\n        )\r\n    }, [apiKeys, organizationId])\r\n\r\n    const [createDialogOpen, setCreateDialogOpen] = useState(false)\r\n    const [displayDialogOpen, setDisplayDialogOpen] = useState(false)\r\n    const [createdApiKey, setCreatedApiKey] = useState(\"\")\r\n\r\n    const handleCreateApiKey = (apiKey: string) => {\r\n        setCreatedApiKey(apiKey)\r\n        setDisplayDialogOpen(true)\r\n    }\r\n\r\n    return (\r\n        <>\r\n            <SettingsCard\r\n                className={className}\r\n                classNames={classNames}\r\n                actionLabel={localization.CREATE_API_KEY}\r\n                description={localization.API_KEYS_DESCRIPTION}\r\n                instructions={localization.API_KEYS_INSTRUCTIONS}\r\n                isPending={isPending}\r\n                title={localization.API_KEYS}\r\n                action={() => setCreateDialogOpen(true)}\r\n                {...props}\r\n            >\r\n                {filteredApiKeys && filteredApiKeys.length > 0 && (\r\n                    <CardContent\r\n                        className={cn(\"grid gap-4\", classNames?.content)}\r\n                    >\r\n                        {filteredApiKeys?.map((apiKey) => (\r\n                            <ApiKeyCell\r\n                                key={apiKey.id}\r\n                                classNames={classNames}\r\n                                apiKey={apiKey}\r\n                                localization={localization}\r\n                                refetch={refetch}\r\n                            />\r\n                        ))}\r\n                    </CardContent>\r\n                )}\r\n            </SettingsCard>\r\n\r\n            <CreateApiKeyDialog\r\n                classNames={classNames}\r\n                localization={localization}\r\n                open={createDialogOpen}\r\n                onOpenChange={setCreateDialogOpen}\r\n                onSuccess={handleCreateApiKey}\r\n                refetch={refetch}\r\n                organizationId={organizationId}\r\n            />\r\n\r\n            <ApiKeyDisplayDialog\r\n                classNames={classNames}\r\n                apiKey={createdApiKey}\r\n                localization={localization}\r\n                open={displayDialogOpen}\r\n                onOpenChange={setDisplayDialogOpen}\r\n            />\r\n        </>\r\n    )\r\n}\r\n",
      "type": "registry:component",
      "target": "components/settings/api-key/api-keys-card.tsx"
    },
    {
      "path": "registry/source/settings/shared/settings-card.tsx",
      "content": "\"use client\"\r\n\r\nimport type { ComponentProps, ReactNode } from \"react\"\r\n\r\nimport { cn } from \"better-auth-ui\"\r\nimport type { AuthLocalization } from \"better-auth-ui\"\r\nimport { Card } from \"@/components/ui/card\"\r\nimport type { UserAvatarClassNames } from \"@/components/user-avatar\"\r\nimport { SettingsCardFooter } from \"./settings-card-footer\"\r\nimport { SettingsCardHeader } from \"./settings-card-header\"\r\n\r\nexport type SettingsCardClassNames = {\r\n    base?: string\r\n    avatar?: UserAvatarClassNames\r\n    button?: string\r\n    cell?: string\r\n    checkbox?: string\r\n    destructiveButton?: string\r\n    content?: string\r\n    description?: string\r\n    dialog?: {\r\n        content?: string\r\n        footer?: string\r\n        header?: string\r\n    }\r\n    error?: string\r\n    footer?: string\r\n    header?: string\r\n    icon?: string\r\n    input?: string\r\n    instructions?: string\r\n    label?: string\r\n    primaryButton?: string\r\n    secondaryButton?: string\r\n    outlineButton?: string\r\n    skeleton?: string\r\n    title?: string\r\n}\r\n\r\nexport interface SettingsCardProps\r\n    extends Omit<ComponentProps<typeof Card>, \"title\"> {\r\n    children?: ReactNode\r\n    className?: string\r\n    classNames?: SettingsCardClassNames\r\n    title?: ReactNode\r\n    description?: ReactNode\r\n    instructions?: ReactNode\r\n    actionLabel?: ReactNode\r\n    isSubmitting?: boolean\r\n    disabled?: boolean\r\n    isPending?: boolean\r\n    optimistic?: boolean\r\n    variant?: \"default\" | \"destructive\"\r\n    localization?: AuthLocalization\r\n    action?: () => Promise<unknown> | unknown\r\n}\r\n\r\nexport function SettingsCard({\r\n    children,\r\n    className,\r\n    classNames,\r\n    title,\r\n    description,\r\n    instructions,\r\n    actionLabel,\r\n    disabled,\r\n    isPending,\r\n    isSubmitting,\r\n    optimistic,\r\n    variant,\r\n    action,\r\n    ...props\r\n}: SettingsCardProps) {\r\n    return (\r\n        <Card\r\n            className={cn(\r\n                \"w-full pb-0 text-start\",\r\n                variant === \"destructive\" && \"border-destructive/40\",\r\n                className,\r\n                classNames?.base\r\n            )}\r\n            {...props}\r\n        >\r\n            <SettingsCardHeader\r\n                classNames={classNames}\r\n                description={description}\r\n                isPending={isPending}\r\n                title={title}\r\n            />\r\n\r\n            {children}\r\n\r\n            <SettingsCardFooter\r\n                classNames={classNames}\r\n                actionLabel={actionLabel}\r\n                disabled={disabled}\r\n                isPending={isPending}\r\n                isSubmitting={isSubmitting}\r\n                instructions={instructions}\r\n                optimistic={optimistic}\r\n                variant={variant}\r\n                action={action}\r\n            />\r\n        </Card>\r\n    )\r\n}\r\n",
      "type": "registry:component",
      "target": "components/settings/shared/settings-card.tsx"
    },
    {
      "path": "registry/source/settings/shared/settings-card-header.tsx",
      "content": "\"use client\"\r\n\r\nimport type { ReactNode } from \"react\"\r\n\r\nimport { cn } from \"better-auth-ui\"\r\nimport { CardDescription, CardHeader, CardTitle } from \"@/components/ui/card\"\r\nimport { Skeleton } from \"@/components/ui/skeleton\"\r\nimport type { SettingsCardClassNames } from \"./settings-card\"\r\n\r\nexport interface SettingsCardHeaderProps {\r\n    className?: string\r\n    classNames?: SettingsCardClassNames\r\n    description?: ReactNode\r\n    isPending?: boolean\r\n    title: ReactNode\r\n}\r\n\r\nexport function SettingsCardHeader({\r\n    className,\r\n    classNames,\r\n    description,\r\n    isPending,\r\n    title\r\n}: SettingsCardHeaderProps) {\r\n    return (\r\n        <CardHeader className={cn(classNames?.header, className)}>\r\n            {isPending ? (\r\n                <>\r\n                    <Skeleton\r\n                        className={cn(\r\n                            \"my-0.5 h-5 w-1/3 md:h-5.5\",\r\n                            classNames?.skeleton\r\n                        )}\r\n                    />\r\n\r\n                    {description && (\r\n                        <Skeleton\r\n                            className={cn(\r\n                                \"mt-1.5 mb-0.5 h-3 w-2/3 md:h-3.5\",\r\n                                classNames?.skeleton\r\n                            )}\r\n                        />\r\n                    )}\r\n                </>\r\n            ) : (\r\n                <>\r\n                    <CardTitle\r\n                        className={cn(\"text-lg md:text-xl\", classNames?.title)}\r\n                    >\r\n                        {title}\r\n                    </CardTitle>\r\n\r\n                    {description && (\r\n                        <CardDescription\r\n                            className={cn(\r\n                                \"text-xs md:text-sm\",\r\n                                classNames?.description\r\n                            )}\r\n                        >\r\n                            {description}\r\n                        </CardDescription>\r\n                    )}\r\n                </>\r\n            )}\r\n        </CardHeader>\r\n    )\r\n}\r\n",
      "type": "registry:component",
      "target": "components/settings/shared/settings-card-header.tsx"
    },
    {
      "path": "registry/source/settings/shared/settings-card-footer.tsx",
      "content": "\"use client\"\r\n\r\nimport type { ReactNode } from \"react\"\r\n\r\nimport { cn } from \"better-auth-ui\"\r\nimport { CardDescription, CardFooter } from \"@/components/ui/card\"\r\nimport { Skeleton } from \"@/components/ui/skeleton\"\r\nimport { SettingsActionButton } from \"./settings-action-button\"\r\nimport type { SettingsCardClassNames } from \"./settings-card\"\r\n\r\nexport interface SettingsCardFooterProps {\r\n    className?: string\r\n    classNames?: SettingsCardClassNames\r\n    actionLabel?: ReactNode\r\n    disabled?: boolean\r\n    instructions?: ReactNode\r\n    isPending?: boolean\r\n    isSubmitting?: boolean\r\n    optimistic?: boolean\r\n    variant?: \"default\" | \"destructive\"\r\n    action?: () => Promise<unknown> | unknown\r\n}\r\n\r\nexport function SettingsCardFooter({\r\n    className,\r\n    classNames,\r\n    actionLabel,\r\n    disabled,\r\n    instructions,\r\n    isPending,\r\n    isSubmitting,\r\n    variant,\r\n    action\r\n}: SettingsCardFooterProps) {\r\n    return (\r\n        <CardFooter\r\n            className={cn(\r\n                \"flex flex-col justify-between gap-4 rounded-b-xl md:flex-row\",\r\n                (actionLabel || instructions) && \"!py-4 border-t\",\r\n                variant === \"destructive\"\r\n                    ? \"border-destructive/30 bg-destructive/15\"\r\n                    : \"bg-sidebar\",\r\n                className,\r\n                classNames?.footer\r\n            )}\r\n        >\r\n            {isPending ? (\r\n                <>\r\n                    {instructions && (\r\n                        <Skeleton\r\n                            className={cn(\r\n                                \"my-0.5 h-3 w-48 max-w-full md:h-4 md:w-56\",\r\n                                classNames?.skeleton\r\n                            )}\r\n                        />\r\n                    )}\r\n\r\n                    {actionLabel && (\r\n                        <Skeleton\r\n                            className={cn(\r\n                                \"h-8 w-14 md:ms-auto\",\r\n                                classNames?.skeleton\r\n                            )}\r\n                        />\r\n                    )}\r\n                </>\r\n            ) : (\r\n                <>\r\n                    {instructions && (\r\n                        <CardDescription\r\n                            className={cn(\r\n                                \"text-center text-muted-foreground text-xs md:text-start md:text-sm\",\r\n                                classNames?.instructions\r\n                            )}\r\n                        >\r\n                            {instructions}\r\n                        </CardDescription>\r\n                    )}\r\n\r\n                    {actionLabel && (\r\n                        <SettingsActionButton\r\n                            classNames={classNames}\r\n                            actionLabel={actionLabel}\r\n                            disabled={disabled}\r\n                            isSubmitting={isSubmitting}\r\n                            variant={variant}\r\n                            onClick={action}\r\n                        />\r\n                    )}\r\n                </>\r\n            )}\r\n        </CardFooter>\r\n    )\r\n}\r\n",
      "type": "registry:component",
      "target": "components/settings/shared/settings-card-footer.tsx"
    },
    {
      "path": "registry/source/settings/shared/settings-action-button.tsx",
      "content": "\"use client\"\r\n\r\nimport { Loader2 } from \"lucide-react\"\r\nimport type { ComponentProps, ReactNode } from \"react\"\r\nimport { useFormState } from \"react-hook-form\"\r\n\r\nimport { cn } from \"better-auth-ui\"\r\nimport { Button } from \"@/components/ui/button\"\r\nimport type { SettingsCardClassNames } from \"./settings-card\"\r\n\r\ninterface SettingsActionButtonProps extends ComponentProps<typeof Button> {\r\n    classNames?: SettingsCardClassNames\r\n    actionLabel: ReactNode\r\n    disabled?: boolean\r\n    isSubmitting?: boolean\r\n}\r\n\r\nexport function SettingsActionButton({\r\n    classNames,\r\n    actionLabel,\r\n    disabled,\r\n    isSubmitting,\r\n    variant,\r\n    onClick,\r\n    ...props\r\n}: SettingsActionButtonProps) {\r\n    if (!onClick) {\r\n        const formState = useFormState()\r\n        isSubmitting = formState.isSubmitting\r\n    }\r\n\r\n    return (\r\n        <Button\r\n            className={cn(\r\n                \"md:ms-auto\",\r\n                classNames?.button,\r\n                variant === \"default\" && classNames?.primaryButton,\r\n                variant === \"destructive\" && classNames?.destructiveButton\r\n            )}\r\n            disabled={isSubmitting || disabled}\r\n            size=\"sm\"\r\n            type={onClick ? \"button\" : \"submit\"}\r\n            variant={variant}\r\n            onClick={onClick}\r\n            {...props}\r\n        >\r\n            {isSubmitting && <Loader2 className=\"animate-spin\" />}\r\n            {actionLabel}\r\n        </Button>\r\n    )\r\n}\r\n",
      "type": "registry:component",
      "target": "components/settings/shared/settings-action-button.tsx"
    },
    {
      "path": "registry/source/account/account-view.tsx",
      "content": "\"use client\"\r\n\r\nimport { MenuIcon } from \"lucide-react\"\r\nimport { useContext, useMemo } from \"react\"\r\nimport { useAuthenticate } from \"better-auth-ui\"\r\nimport { AuthUIContext } from \"better-auth-ui\"\r\nimport { cn, getViewByPath } from \"better-auth-ui\"\r\nimport type { AuthLocalization } from \"better-auth-ui\"\r\nimport type { AccountViewPath } from \"better-auth-ui\"\r\nimport { OrganizationsCard } from \"@/components/organization/organizations-card\"\r\nimport { UserInvitationsCard } from \"@/components/organization/user-invitations-card\"\r\nimport { AccountSettingsCards } from \"@/components/settings/account-settings-cards\"\r\nimport { ApiKeysCard } from \"@/components/settings/api-key/api-keys-card\"\r\nimport { SecuritySettingsCards } from \"@/components/settings/security-settings-cards\"\r\nimport type { SettingsCardClassNames } from \"@/components/settings/shared/settings-card\"\r\nimport { Button } from \"@/components/ui/button\"\r\nimport {\r\n    Drawer,\r\n    DrawerContent,\r\n    DrawerHeader,\r\n    DrawerTitle,\r\n    DrawerTrigger\r\n} from \"@/components/ui/drawer\"\r\nimport { Label } from \"@/components/ui/label\"\r\n\r\nexport interface AccountViewProps {\r\n    className?: string\r\n    classNames?: {\r\n        base?: string\r\n        cards?: string\r\n        drawer?: { menuItem?: string }\r\n        sidebar?: { base?: string; button?: string; buttonActive?: string }\r\n        card?: SettingsCardClassNames\r\n    }\r\n    localization?: AuthLocalization\r\n    path?: string\r\n    pathname?: string\r\n    view?: AccountViewPath\r\n    hideNav?: boolean\r\n}\r\n\r\nexport function AccountView({\r\n    className,\r\n    classNames,\r\n    localization: localizationProp,\r\n    path: pathProp,\r\n    pathname,\r\n    view: viewProp,\r\n    hideNav\r\n}: AccountViewProps) {\r\n    const {\r\n        apiKey,\r\n        localization: contextLocalization,\r\n        organization,\r\n        account: accountOptions,\r\n        Link\r\n    } = useContext(AuthUIContext)\r\n\r\n    if (!accountOptions) {\r\n        return null\r\n    }\r\n\r\n    useAuthenticate()\r\n\r\n    const localization = useMemo(\r\n        () => ({ ...contextLocalization, ...localizationProp }),\r\n        [contextLocalization, localizationProp]\r\n    )\r\n\r\n    const path = pathProp ?? pathname?.split(\"/\").pop()\r\n\r\n    const view =\r\n        viewProp || getViewByPath(accountOptions.viewPaths, path!) || \"SETTINGS\"\r\n\r\n    const navItems: {\r\n        view: AccountViewPath\r\n        label: string\r\n    }[] = [\r\n        { view: \"SETTINGS\", label: localization.ACCOUNT },\r\n        { view: \"SECURITY\", label: localization.SECURITY }\r\n    ]\r\n\r\n    if (apiKey) {\r\n        navItems.push({\r\n            view: \"API_KEYS\",\r\n            label: localization.API_KEYS\r\n        })\r\n    }\r\n\r\n    if (organization) {\r\n        navItems.push({\r\n            view: \"ORGANIZATIONS\",\r\n            label: localization.ORGANIZATIONS\r\n        })\r\n    }\r\n\r\n    return (\r\n        <div\r\n            className={cn(\r\n                \"flex w-full grow flex-col gap-4 md:flex-row md:gap-12\",\r\n                className,\r\n                classNames?.base\r\n            )}\r\n        >\r\n            {!hideNav && (\r\n                <div className=\"flex justify-between gap-2 md:hidden\">\r\n                    <Label className=\"font-semibold text-base\">\r\n                        {navItems.find((i) => i.view === view)?.label}\r\n                    </Label>\r\n\r\n                    <Drawer>\r\n                        <DrawerTrigger asChild>\r\n                            <Button variant=\"outline\">\r\n                                <MenuIcon />\r\n                            </Button>\r\n                        </DrawerTrigger>\r\n                        <DrawerContent>\r\n                            <DrawerHeader>\r\n                                <DrawerTitle className=\"hidden\">\r\n                                    {localization.SETTINGS}\r\n                                </DrawerTitle>\r\n                            </DrawerHeader>\r\n                            <div className=\"flex flex-col px-4 pb-4\">\r\n                                {navItems.map((item) => (\r\n                                    <Link\r\n                                        key={item.view}\r\n                                        href={`${accountOptions?.basePath}/${accountOptions?.viewPaths[item.view]}`}\r\n                                    >\r\n                                        <Button\r\n                                            size=\"lg\"\r\n                                            className={cn(\r\n                                                \"w-full justify-start px-4 transition-none\",\r\n                                                classNames?.drawer?.menuItem,\r\n                                                view === item.view\r\n                                                    ? \"font-semibold\"\r\n                                                    : \"text-foreground/70\"\r\n                                            )}\r\n                                            variant=\"ghost\"\r\n                                        >\r\n                                            {item.label}\r\n                                        </Button>\r\n                                    </Link>\r\n                                ))}\r\n                            </div>\r\n                        </DrawerContent>\r\n                    </Drawer>\r\n                </div>\r\n            )}\r\n\r\n            {!hideNav && (\r\n                <div className=\"hidden md:block\">\r\n                    <div\r\n                        className={cn(\r\n                            \"flex w-48 flex-col gap-1 lg:w-60\",\r\n                            classNames?.sidebar?.base\r\n                        )}\r\n                    >\r\n                        {navItems.map((item) => (\r\n                            <Link\r\n                                key={item.view}\r\n                                href={`${accountOptions?.basePath}/${accountOptions?.viewPaths[item.view]}`}\r\n                            >\r\n                                <Button\r\n                                    size=\"lg\"\r\n                                    className={cn(\r\n                                        \"w-full justify-start px-4 transition-none\",\r\n                                        classNames?.sidebar?.button,\r\n                                        view === item.view\r\n                                            ? \"font-semibold\"\r\n                                            : \"text-foreground/70\",\r\n                                        view === item.view &&\r\n                                            classNames?.sidebar?.buttonActive\r\n                                    )}\r\n                                    variant=\"ghost\"\r\n                                >\r\n                                    {item.label}\r\n                                </Button>\r\n                            </Link>\r\n                        ))}\r\n                    </div>\r\n                </div>\r\n            )}\r\n\r\n            {view === \"SETTINGS\" && (\r\n                <AccountSettingsCards\r\n                    classNames={classNames}\r\n                    localization={localization}\r\n                />\r\n            )}\r\n\r\n            {view === \"SECURITY\" && (\r\n                <SecuritySettingsCards\r\n                    classNames={classNames}\r\n                    localization={localization}\r\n                />\r\n            )}\r\n\r\n            {view === \"API_KEYS\" && (\r\n                <ApiKeysCard\r\n                    classNames={classNames?.card}\r\n                    localization={localization}\r\n                />\r\n            )}\r\n\r\n            {view === \"ORGANIZATIONS\" && organization && (\r\n                <div className=\"grid w-full gap-4 md:gap-6\">\r\n                    <OrganizationsCard\r\n                        classNames={classNames?.card}\r\n                        localization={localization}\r\n                    />\r\n\r\n                    <UserInvitationsCard\r\n                        classNames={classNames?.card}\r\n                        localization={localization}\r\n                    />\r\n                </div>\r\n            )}\r\n        </div>\r\n    )\r\n}\r\n",
      "type": "registry:component",
      "target": "components/account/account-view.tsx"
    }
  ],
  "type": "registry:block"
}